{"id":"5728bff7-60e9-e8c0-a0f1-901061725442","Content":[{"Language":"nl-NL","Content":"[$BOX]\n\t[$CELL]\n\t\t[$BLOCK]\n\n\t\t\t<h3>Ganglion</h3>\n\t\t\t<p>Een ganglion is een bobbeltje dat zich bevindt aan de pols, vinger of voet. Het is een soort uitstulping van de peesschede of het gewrichtskapsel en kan zowel plotseling als geleidelijk ontstaan. Een ganglion geeft meestal geen klachten, maar kan in de weg zitten. Het kan geen kwaad en verdwijnt in de helft van de gevallen vanzelf.</p>\n\n\t\t[$/BLOCK]\n\t[$/CELL]\n\t[$CELL]\n\n\t\t[$IMG(\"/media/Images/shutterstock_1070791859.jpg\";400,300)]\n\n\t[$/CELL]\n[$/BOX]","Name":"Ganglion"}]}