{"id":"591c8bcd-b4cc-25b1-4635-0aa57412deb5","Content":[{"Language":"nl-NL","Content":"[$BOX]\n\t[$CELL]\n\t\t[$BLOCK]\n\n\t\t\t<h3>Behandeling van chronische lymfatische leukemie</h3>\n\t\t\t<p>Chronische lymfatische leukemie wordt ingedeeld in <strong>stadia</strong>. Welke behandeling wordt gestart, is afhankelijk van het ziektestadium. De ziektestadia geven de uitgebreidheid van de ziekte weer. Het stadium van chronische lymfatische leukemie bij een patiënt wordt bepaald aan de hand van:</p>\n\t\t\t<ul>\n\t\t\t\t<li>Hoeveelheid lymfocyten in het bloed;</li>\n\t\t\t\t<li>Wel/niet aanwezig zijn van vergrote lymfeklieren;</li>\n\t\t\t\t<li>Wel/niet aanwezig zijn van een vergrote milt;</li>\n\t\t\t\t<li>Wel/niet aanwezig zijn van een vergrote lever.</li>\n\t\t\t</ul>\n\n\t\t[$/BLOCK]\n\t[$/CELL]\n\t[$CELL]\n\n\t\t[$IMG(\"/media/Images/shutterstock_290588615.jpg\";200,300)]\n\n\t[$/CELL]\n[$/BOX]\n\n[$BOX]\n\t[$CELL]\n\t\t[$BLOCK]\n\n\t\t\t<p>Chronische lymfatische leukemie kan zich langzaam ontwikkelen. Als de ziekte niet ver is uitgebreid kan de arts er daarom voor kiezen om af te wachten. Afwachten betekent dat de patiënt regelmatig wordt gecontroleerd, terwijl er geen gerichte behandeling tegen de chronische lymfatische leukemie wordt gestart. Doorgaans geldt dat hoe verder de ziekte is uitgebreid, hoe eerder de arts zal starten met behandeling.</p>\n\t\t\t<p><strong>Behandelopties </strong>voor chronische lymfatische leukemie zijn:</p>\n\t\t\t<ul>\n\t\t\t\t<li><strong>Chemotherapie</strong>;</li>\n\t\t\t\t<li><strong>Afweerstoffen (immunoglobulinen)</strong>, gericht tegen kwaadaardige B-cellen;</li>\n\t\t\t\t<li><strong>Combinatie van bovenstaande</strong>.</li>\n\t\t\t</ul>\n\t\t\t<p>Een <strong>stamceltransplantatie</strong> is een behandeloptie in het geval van:</p>\n\t\t\t<ul>\n\t\t\t\t<li>Onvoldoende effect van de behandeling tot nu toe;</li>\n\t\t\t\t<li>Het terugkomen van de chronische lymfatische leukemie (een recidief).</li>\n\t\t\t</ul>\n\n\t\t[$/BLOCK]\n\t[$/CELL]\n[$/BOX] ","Name":"Behandeling chronische lymfatische leukemie"}]}