{"id":"5963dc37-536e-d356-f293-c4a173f5c190","Content":[{"Language":"nl-NL","Content":"[$BOX]\n\t[$CELL]\n\t\t[$BLOCK]\n\n\t\t\t<h3>Opslag binnen</h3>\n\t\t\t<p>Ook de opslag van gascilinders moet aan strenge eisen voldoen. De gassen die via cilinderbatterijen worden gedistribueerd staan opgeslagen in <em>keuzegaskasten. </em>Dit zijn kasten met een brandwerende deur. Om eventuele ophoping van gas door lekkages te vermijden, worden deze kasten geventileerd. Als een cilinder omvalt terwijl deze aangesloten is, kan de slang scheuren. Om deze reden dienen aangesloten gascilinders met een ketting aan de muur bevestigd te worden. Oxiderende en brandwerende gassen worden gescheiden bewaard.\t\n\t\t\t[$IMG(\"/media/Images/shutterstock_35594518.jpg\";449,300)]\n        \t<table border=\"0\" cellspacing=\"5\" cellpadding=\"0\" width=\"100%\">\n              \t<tr>\n                   \t<td width=\"50%\" align=\"center\">[$IMG(\"/media/Images/Opslag binnen 1.jpg\";442,300)]</td>\n                   \t<td width=\"50%\" align=\"center\">[$IMG(\"/media/Images/Opslag binnen 2.jpg\";442,300)]</td>\n                </tr>\n                <tr>\n                   \t<td width=\"50%\" align=\"center\">[$IMG(\"/media/Images/Opslag binnen 3.jpg\";146,300;3)]</td>\n                   \t<td width=\"50%\" align=\"center\">[$IMG(\"/media/Images/Opslag binnen 4.jpg\";146,300;3)]</td>\n                </tr>\n            </table>\n\n\t\t[$/BLOCK]\n\t[$/CELL]\n[$/BOX]","Name":"Opslag binnen"}]}