{"id":"58357dd4-3360-08a8-f822-364124bcea03","Content":[{"Language":"nl-NL","Content":"[$BOX]\n\t[$CELL]\n\t\t[$BLOCK]\n\n\t\t\t<h3>Warmteverlies via het huidoppervlak</h3>\n\t\t\t<p>Een groot deel van de geproduceerde lichaamswarmte is afkomstig van de interne organen en weefsels, waaronder de lever, hersenen, het hart en de spieren. Een deel van deze warmte wordt gebruikt voor metabole processen; het resterende deel wordt uitgescheiden. De huid en het onderhuids vet dienen als isolatoren: ze beschermen het lichaam tegen warmteverlies.</p>\n\t\t\t<p>Via het bloed wordt de warmte getransporteerd van de inwendige organen naar de huid en slijmvliezen. Hier wordt de overtollige warmte afgegeven.</p>\n\t\t\t<p>Verschillende manieren bestaan waarop de huid warmte afgeeft aan de omgeving:</p>\n\t\t\t<ul>\n\t\t\t\t<li>radiatie (straling);</li>\n\t\t\t\t<li>conductie (geleiding);</li>\n\t\t\t\t<li>convectie (stroming);</li>\n\t\t\t\t<li>evaporatie (verdamping).</li>\n\t\t\t</ul>\n\n\t\t[$/BLOCK]\n\t[$/CELL]\n\t[$CELL]\n\n\t\t[$IMG(\"/media/Images/Warmteverlies via het huidoppervlak_swf.jpg\";218,300;3)]\n\n\t[$/CELL]\n[$/BOX] ","Name":"Warmteverlies via het huidoppervlak"}]}