{"id":"593a2c77-531e-df52-6042-12e02314b610","Content":[{"Language":"nl-NL","Content":"[$BOX]\n\t[$CELL]\n\t\t[$BLOCK]\n\n\t\t\t<h3>Sociale interacties</h3>\n\t\t\t<p>Interactie betekent hoe je op andere mensen reageert en hoe je met andere mensen omgaat. Bij deze dimensie onderzoek je de sociale relaties van de zorgvrager. Je kijkt ook naar de maatschappelijke participatie van de zorgvrager. Participatie betekent meedoen. Bij maatschappelijke participatie onderzoek je het sociale leven van de zorgvrager. Voorbeelden van maatschappelijk participeren zijn:</p>\n\t\t\t<ul>\n\t\t\t\t<li>werk;</li>\n\t\t\t\t<li>lid zijn van een club;</li>\n\t\t\t\t<li>andere activiteiten die de zorgvrager graag doet die met anderen te maken hebben.</li>\n\t\t\t</ul>\n\n\t\t[$/BLOCK]\n\t[$/CELL]\n[$/BOX]\n","Name":"Sociale interacties"}]}