{"id":"59185e37-5416-79ae-fc87-42dfc83fa22d","Content":[{"Language":"nl-NL","Content":"[$BOX]\n\t[$CELL]\n\t\t[$BLOCK]\n\n\t\t\t<h3>15.7.6 Activiteit van het maagdarmstelsel</h3>\n\t\t\t<p>Binnen het maagdarmstelsel zorgen de impulsen van de parasympathische zenuwen voor een algehele verhoging van de peristaltiek en de ontspanning van belangrijke sfincters, terwijl de sympathische zenuwen zorgen voor een vermindering van de motiliteit en een algehele afname van de activiteit van het maagdarmstelsel.</p>\n\n\t\t[$/BLOCK]\n\t[$/CELL]\n\t[$CELL]\n\n\t\t[$IMG(\"/media/Images/shutterstock_1774328747.jpg\";212,300)]\n\n\t[$/CELL]\n[$/BOX]\n","Name":"15.7.6 Activiteit van het maagdarmstelsel"}]}