{"id":"6027ebb1-e750-33aa-aed8-cf1f2205d8c5","Content":[{"Language":"se-SE","Content":"[$BOX]\n\t[$CELL]\n\t\t[$BLOCK]\n\n\t\t\t<h3>Nervsystemets uppgifter och organisation</h3>\n\t\t\t<p>I nervsystemet ska information, b&aring;de fr&aring;n kroppens inre och fr&aring;n v&auml;rlden utanf&ouml;r, mottas och bearbetas samt integreras. En del av informationen n&aring;r v&aring;rt medvetande, men det mesta av informationen anv&auml;nds helt omedvetet f&ouml;r olika funktioner. Till exempel om en person vistas utomhus i kallt v&auml;der med f&ouml;r tunn kl&auml;dsel hotas kroppens temperatur. En del av nervsystemet f&ouml;rmedlar att huden kyls och en annan del bearbetar denna information. En viss del av informationen n&aring;r medvetandet, personen k&auml;nner sig kall och g&ouml;r n&aring;gra viljestyrda muskelr&ouml;relser i form av &rdquo;&aring;karbrasor&rdquo;. En annan del av informationen leder till helt omedvetna &aring;tg&auml;rder, exempelvis sammandragning av blodk&auml;rl i huden och &ouml;kad &auml;mnesoms&auml;ttning. Nervsystemets uppgift att integrera individen med den yttre milj&ouml;n i syfte att kroppens homeostas ska uppr&auml;tth&aring;llas kan ses i m&aring;nga olika funktionssammanhang. Vid f&ouml;r&auml;ndringar i den omgivande milj&ouml;n reagerar och agerar nervsystemet snabbt, vilket &auml;r en f&ouml;ruts&auml;ttning f&ouml;r organismens &ouml;verlevnad.</p>\n\t\t\t<p>Nervsystemet delas, som redan n&auml;mnts, in i tv&aring; strukturella enheter: <em>centrala nervsystemet</em>, CNS, och <em>perifera nervsystemet</em>, PNS. CNS best&aring;r av hj&auml;rna och ryggm&auml;rg. PNS innefattas av de nerver som l&ouml;per ut fr&aring;n hj&auml;rna och ryggm&auml;rg (kranialnerver och perifera nerver) till olika delar av kroppen. Vidare kan nervsystemet indelas i tv&aring; funktionella enheter: en <em>somatomotorisk del </em>och en <em>autonom del</em>, autonoma nervsystemet eller ANS. Den somatomotoriska delen kontrollerar skelettmuskulaturens r&ouml;relser och &auml;r till st&ouml;rsta delen viljestyrd. R&ouml;relsemoment som inte &auml;r viljestyrda &auml;r de reflexer som utf&ouml;rs av skelettmuskulaturen. ANS st&aring;r i stort sett utanf&ouml;r viljans kontroll och styr aktiviteten hos hj&auml;rtmuskulaturen, glatt muskulatur och k&ouml;rtlar. De ut&aring;tledande nerverna kallas <em>efferenter</em>. F&ouml;rutom ut&aring;tg&aring;ende impulstrafik l&ouml;per det &auml;ven in&aring;tg&aring;ende sensorisk impulstrafik i den somatiska delen och i ANS. Den sensoriska impulstrafiken informerar det centrala nervsystemet om vad som h&auml;nder i kroppen och utanf&ouml;r. De sensoriska in&aring;tledande nerverna kallas f&ouml;r <em>afferenter</em>.</p>\n\n\t\t[$/BLOCK]\n\t[$/CELL]\n[$/BOX]","Name":"Nervsystemets  uppgifter och organisation"}]}